grai_source_redshift/__init__.py
grai_source_redshift/adapters.py
grai_source_redshift/base.py
grai_source_redshift/loader.py
grai_source_redshift/models.py
grai_source_redshift/package_definitions.py
grai_source_redshift-0.1.1.dist-info/METADATA
grai_source_redshift-0.1.1.dist-info/WHEEL
grai_source_redshift-0.1.1.dist-info/RECORD
