Metadata-Version: 2.1
Name: grai_source_redshift
Version: 0.1.1
Summary: 
Home-page: https://www.grai.io/
License: Elastic-2.0
Author: Ian Eaves
Author-email: ian@grai.io
Requires-Python: >=3.8,<4.0
Classifier: License :: Other/Proprietary License
Classifier: Programming Language :: Python :: 3
Classifier: Programming Language :: Python :: 3.8
Classifier: Programming Language :: Python :: 3.9
Classifier: Programming Language :: Python :: 3.10
Classifier: Programming Language :: Python :: 3.11
Requires-Dist: grai-schemas (>=0.2.7-alpha1,<0.3.0)
Requires-Dist: multimethod (>=1.8,<2.0)
Requires-Dist: pydantic[dotenv] (>=1.10.7,<2.0.0)
Requires-Dist: redshift-connector (>=2.0.911,<3.0.0)
Project-URL: Documentation, https://docs.grai.io/
Project-URL: Repository, https://github.com/grai-io/grai-core/tree/master/grai-integrations/source-redshift
